Metadata-Version: 2.4
Name: petal-etl-composer
Version: 0.1.11
Summary: Composable ETL Logic Layer
Author-email: Yuval Timen <yuvaltimen@gmail.com>
License: MIT
Requires-Python: >=3.8
